gsub/__init__.py
gsub/main.py
gsub-0.0.0.dist-info/DESCRIPTION.rst
gsub-0.0.0.dist-info/entry_points.txt
gsub-0.0.0.dist-info/METADATA
gsub-0.0.0.dist-info/metadata.json
gsub-0.0.0.dist-info/RECORD
gsub-0.0.0.dist-info/top_level.txt
gsub-0.0.0.dist-info/WHEEL
gsub-0.0.0.dist-info/zip-safe
